pipelines_utils/BasicObjectWriter.py
pipelines_utils/StreamJsonListLoader.py
pipelines_utils/TsvWriter.py
pipelines_utils/TypedColumnReader.py
pipelines_utils/__init__.py
pipelines_utils/file_utils.py
pipelines_utils/parameter_utils.py
pipelines_utils/utils.py
im_pipelines_utils-2.4.8.dist-info/LICENSE.txt
im_pipelines_utils-2.4.8.dist-info/METADATA
im_pipelines_utils-2.4.8.dist-info/WHEEL
im_pipelines_utils-2.4.8.dist-info/top_level.txt
im_pipelines_utils-2.4.8.dist-info/RECORD
