Metadata-Version: 2.1
Name: im-pipelines-utils
Version: 2.4.8
Summary: Utilities for Informatics Matters Pipelines
Home-page: https://github.com/InformaticsMatters/pipelines-utils
Author: Alan Christie
Author-email: achristie@informaticsmatters.com
License: Copyright (C) 2018 Informatics Matters Ltd. All rights reserved.
Keywords: pipelines
Platform: any
Classifier: Development Status :: 5 - Production/Stable
Classifier: Environment :: Console
Classifier: Intended Audience :: Developers
Classifier: License :: OSI Approved :: MIT License
Classifier: Programming Language :: Python :: 2.7
Classifier: Programming Language :: Python :: 3.5
Classifier: Programming Language :: Python :: 3.6
Classifier: Topic :: Software Development :: Build Tools
Requires-Python: >=2.7, !=3.0.*, !=3.1.*, !=3.2.*, !=3.3.*, != 3.4.*, <4
Requires-Dist: future (>=0.16.0)
